{"openapi":"3.1.0","info":{"title":"OpenAPI definition","version":"v0"},"servers":[{"url":"http://localhost:8080","description":"Generated server url"}],"paths":{"/api/productos/estado/{idProducto}":{"put":{"tags":["producto-controller"],"operationId":"cambiarEstadoProducto","parameters":[{"name":"idProducto","in":"path","required":true,"schema":{"type":"integer","format":"int64"}}],"requestBody":{"content":{"application/json":{"schema":{"type":"string","enum":["DISPONIBLE","NO_DISPONIBLE"]}}},"required":true},"responses":{"200":{"description":"OK","content":{"*/*":{"schema":{"type":"object"}}}}}}},"/api/productos/actualizar/{idProducto}":{"put":{"tags":["producto-controller"],"operationId":"actualizarProducto","parameters":[{"name":"idProducto","in":"path","required":true,"schema":{"type":"integer","format":"int64"}}],"requestBody":{"content":{"application/json":{"schema":{"$ref":"#/components/schemas/Producto"}}},"required":true},"responses":{"200":{"description":"OK","content":{"*/*":{"schema":{"type":"object"}}}}}}},"/api/categorias/actualizar/{idCategoria}":{"put":{"tags":["categoria-controller"],"operationId":"actualizarCategoria","parameters":[{"name":"idCategoria","in":"path","required":true,"schema":{"type":"integer","format":"int64"}}],"requestBody":{"content":{"application/json":{"schema":{"$ref":"#/components/schemas/Categoria"}}},"required":true},"responses":{"200":{"description":"OK","content":{"*/*":{"schema":{"type":"object"}}}}}}},"/api/productos/registrar":{"post":{"tags":["producto-controller"],"operationId":"registrarProducto","requestBody":{"content":{"application/json":{"schema":{"$ref":"#/components/schemas/Producto"}}},"required":true},"responses":{"200":{"description":"OK","content":{"*/*":{"schema":{"type":"object"}}}}}}},"/api/categorias/crear":{"post":{"tags":["categoria-controller"],"operationId":"crearCategoria","requestBody":{"content":{"application/json":{"schema":{"$ref":"#/components/schemas/Categoria"}}},"required":true},"responses":{"200":{"description":"OK","content":{"*/*":{"schema":{"$ref":"#/components/schemas/Categoria"}}}}}}},"/api/productos":{"get":{"tags":["producto-controller"],"operationId":"listarProductos","responses":{"200":{"description":"OK","content":{"*/*":{"schema":{"type":"array","items":{"$ref":"#/components/schemas/Producto"}}}}}}}},"/api/productos/estado/{estadoProducto}":{"get":{"tags":["producto-controller"],"operationId":"listarProductosPorEstado","parameters":[{"name":"estadoProducto","in":"path","required":true,"schema":{"type":"string","enum":["DISPONIBLE","NO_DISPONIBLE"]}}],"responses":{"200":{"description":"OK","content":{"*/*":{"schema":{"type":"array","items":{"$ref":"#/components/schemas/Producto"}}}}}}}},"/api/productos/buscar/nombre/{nombre}":{"get":{"tags":["producto-controller"],"operationId":"listarPorNombre","parameters":[{"name":"nombre","in":"path","required":true,"schema":{"type":"string"}}],"responses":{"200":{"description":"OK","content":{"*/*":{"schema":{"type":"object"}}}}}}},"/api/productos/buscar/id/{idProducto}":{"get":{"tags":["producto-controller"],"operationId":"buscarPorId","parameters":[{"name":"idProducto","in":"path","required":true,"schema":{"type":"integer","format":"int64"}}],"responses":{"200":{"description":"OK","content":{"*/*":{"schema":{"type":"object"}}}}}}},"/api/categorias":{"get":{"tags":["categoria-controller"],"operationId":"listarCategoria","responses":{"200":{"description":"OK","content":{"*/*":{"schema":{"type":"array","items":{"$ref":"#/components/schemas/Categoria"}}}}}}}},"/api/categorias/buscar/categoria/{idCategoria}":{"get":{"tags":["categoria-controller"],"operationId":"categoriaPorId","parameters":[{"name":"idCategoria","in":"path","required":true,"schema":{"type":"integer","format":"int64"}}],"responses":{"200":{"description":"OK","content":{"*/*":{"schema":{"type":"object"}}}}}}},"/api/productos/{idProducto}":{"delete":{"tags":["producto-controller"],"operationId":"eliminarProducto","parameters":[{"name":"idProducto","in":"path","required":true,"schema":{"type":"integer","format":"int64"}}],"responses":{"200":{"description":"OK","content":{"*/*":{"schema":{"type":"object"}}}}}}},"/api/categorias/{idCategoria}":{"delete":{"tags":["categoria-controller"],"operationId":"eliminarCategoria","parameters":[{"name":"idCategoria","in":"path","required":true,"schema":{"type":"integer","format":"int64"}}],"responses":{"200":{"description":"OK","content":{"*/*":{"schema":{"type":"object"}}}}}}}},"components":{"schemas":{"Categoria":{"type":"object","properties":{"idCategoria":{"type":"integer","format":"int64"},"nombreCategoria":{"type":"string"}}},"Producto":{"type":"object","properties":{"idProducto":{"type":"integer","format":"int64"},"nombreProducto":{"type":"string"},"descripcion":{"type":"string"},"precio":{"type":"number","format":"double"},"cantidad":{"type":"integer","format":"int32"},"estadoProducto":{"type":"string","enum":["DISPONIBLE","NO_DISPONIBLE"]},"categoria":{"$ref":"#/components/schemas/Categoria"}}}}}}